fastmodel/__init__.py
fastmodel/__main__.py
fastmodel/cli.py
fastmodel/config.py
fastmodel/exceptions.py
fastmodel/fastapi/__init__.py
fastmodel/fastapi/io.py
fastmodel/fastapi/utils.py
fastmodel/routers/__init__.py
fastmodel/routers/base.py
fastmodel/security.py
fastmodel/serve.py
fastmodel/status_code.py
fastmodel/utils/__init__.py
fastmodel/utils/async_model.py
fastmodel/utils/importer.py
fastmodel-0.1.0.post1.dist-info/METADATA
fastmodel-0.1.0.post1.dist-info/WHEEL
fastmodel-0.1.0.post1.dist-info/entry_points.txt
fastmodel-0.1.0.post1.dist-info/RECORD
