Metadata-Version: 2.3
Name: fastmodel
Version: 0.1.0.post1
Summary: a FastAPI model generator and Ai model serving
License: MIT
Author: Iito
Requires-Python: >=3.10,<3.12
Classifier: Framework :: FastAPI
Classifier: Intended Audience :: Developers
Classifier: Intended Audience :: Information Technology
Classifier: Intended Audience :: System Administrators
Classifier: License :: OSI Approved :: MIT License
Classifier: Operating System :: OS Independent
Classifier: Programming Language :: Python
Classifier: Programming Language :: Python :: 3
Classifier: Programming Language :: Python :: 3.10
Classifier: Programming Language :: Python :: 3.11
Classifier: Topic :: Software Development
Classifier: Topic :: Software Development :: Libraries
Classifier: Topic :: Software Development :: Libraries :: Application Frameworks
Classifier: Topic :: Software Development :: Libraries :: Python Modules
Requires-Dist: art (>=6)
Requires-Dist: fastapi (>0.95.1)
Requires-Dist: pydantic (>=2.4)
Requires-Dist: python-multipart (>=0.0.6)
Requires-Dist: uvicorn (>=0.22.0)
Project-URL: Repository, https://github.com/Iito/fastmodel
